LICENSE.txt
README.rst
setup.py
prometheus_aioredis_client/__init__.py
prometheus_aioredis_client/metrics.py
prometheus_aioredis_client/registry.py
prometheus_aioredis_client/task_manager.py
prometheus_aioredis_client/values.py
prometheus_aioredis_client.egg-info/PKG-INFO
prometheus_aioredis_client.egg-info/SOURCES.txt
prometheus_aioredis_client.egg-info/dependency_links.txt
prometheus_aioredis_client.egg-info/requires.txt
prometheus_aioredis_client.egg-info/top_level.txt