Metadata-Version: 2.1
Name: prometheus-aioredis-client
Version: 0.3.0
Summary: Python prometheus multiprocessing client which used redis as metric storage.
Home-page: https://github.com/belousovalex/prometheus_aioredis_client
Author: Belousov Alex
Author-email: belousov.aka.alfa@gmail.com
License: Apache 2
License-File: LICENSE.txt
